[
  {
    "src": "https://ik.imagekit.io/thewrightdesigns/neon-productions/home page/home-slideshow1.jpg",
    "alt": "Neon Productions photography"
  },
  {
    "src": "https://ik.imagekit.io/thewrightdesigns/neon-productions/home page/home-slideshow2.jpg",
    "alt": "Neon Productions photography"
  },
  {
    "src": "https://ik.imagekit.io/thewrightdesigns/neon-productions/home page/home-slideshow3.jpg",
    "alt": "Neon Productions photography"
  },
  {
    "src": "https://ik.imagekit.io/thewrightdesigns/neon-productions/home page/home-slideshow4.jpg",
    "alt": "Neon Productions photography"
  },
  {
    "src": "https://ik.imagekit.io/thewrightdesigns/neon-productions/home page/home-slideshow5.jpg",
    "alt": "Neon Productions photography"
  },
  {
    "src": "https://ik.imagekit.io/thewrightdesigns/neon-productions/home page/home-slideshow16.jpg",
    "alt": "Neon Productions photography"
  },
  {
    "src": "https://ik.imagekit.io/thewrightdesigns/neon-productions/home page/home-slideshow7.jpg",
    "alt": "Neon Productions photography"
  },
  {
    "src": "https://ik.imagekit.io/thewrightdesigns/neon-productions/home page/home-slideshow8.jpg",
    "alt": "Neon Productions photography"
  },
  {
    "src": "https://ik.imagekit.io/thewrightdesigns/neon-productions/home page/home-slideshow9.jpg",
    "alt": "Neon Productions photography"
  },
  {
    "src": "https://ik.imagekit.io/thewrightdesigns/neon-productions/home page/home-slideshow10.jpg",
    "alt": "Neon Productions photography"
  },
  {
    "src": "https://ik.imagekit.io/thewrightdesigns/neon-productions/home page/home-slideshow11.jpg",
    "alt": "Neon Productions photography"
  },
  {
    "src": "https://ik.imagekit.io/thewrightdesigns/neon-productions/home page/home-slideshow13.jpg",
    "alt": "Neon Productions photography"
  },
  {
    "src": "https://ik.imagekit.io/thewrightdesigns/neon-productions/home page/home-slideshow14.jpg",
    "alt": "Neon Productions photography"
  },
  {
    "src": "https://ik.imagekit.io/thewrightdesigns/neon-productions/home page/home-slideshow15.jpg",
    "alt": "Neon Productions photography"
  },
  {
    "src": "https://ik.imagekit.io/thewrightdesigns/neon-productions/home page/home-slideshow16.jpg",
    "alt": "Neon Productions photography"
  },
  {
    "src": "https://ik.imagekit.io/thewrightdesigns/neon-productions/home page/home-slideshow12.jpg",
    "alt": "Neon Productions photography"
  }
]
